x2t/__init__.py
x2t/logger.py
x2t/toolkit.py
x2ttech-0.4.2.dist-info/licenses/LICENSE
x2ttech-0.4.2.dist-info/METADATA
x2ttech-0.4.2.dist-info/WHEEL
x2ttech-0.4.2.dist-info/top_level.txt
x2ttech-0.4.2.dist-info/RECORD
