Metadata-Version: 2.4
Name: x2ttech
Version: 0.4.2
Summary: A Python library for amazing functionality
Author-email: x2T Technique <x2t.technique@gmail.com>
Maintainer-email: Bùi Đức Tuấn <buiductuan12081995@gmail.com>, Nguyễn Thị Phương Tâm <phuongtam128@gmail.com>
License: MIT
Project-URL: Homepage, https://x2t.tech
Project-URL: Repository, https://github.com/x2TTechnique/x2t-pypi
Project-URL: Issues, https://github.com/x2TTechnique/x2t-pypi/issues
Project-URL: Changelog, https://github.com/x2TTechnique/x2t-pypi/blob/master/CHANGELOG.md
Keywords: erp,tiktok,odoo
Classifier: Programming Language :: Python :: 3
Classifier: Programming Language :: Python :: 3.6
Classifier: Programming Language :: Python :: 3.7
Classifier: Programming Language :: Python :: 3.8
Classifier: Programming Language :: Python :: 3.9
Classifier: Programming Language :: Python :: 3.10
Classifier: Programming Language :: Python :: 3.11
Classifier: Programming Language :: Python :: 3.12
Classifier: License :: OSI Approved :: MIT License
Classifier: Operating System :: OS Independent
Classifier: Development Status :: 4 - Beta
Classifier: Intended Audience :: Developers
Requires-Python: >=3.8
License-File: LICENSE
Requires-Dist: requests
Requires-Dist: unidecode
Requires-Dist: loguru
Requires-Dist: pillow
Dynamic: license-file
